{
  "last_updated": "2026-05-07",
  "oos_start": "2014-07-29",
  "oos_end": "2026-05-07",
  "strategy": {
    "cagr_pct": 9.7795,
    "ann_vol_pct": 10.8805,
    "max_drawdown_pct": -16.7963,
    "calmar": 0.5822,
    "sharpe": 0.9139,
    "sortino": 0.9889,
    "skewness": -0.7279,
    "excess_kurtosis": 9.5886,
    "exposure_long_pct": 75.1519,
    "exposure_tbill_pct": 24.8481,
    "n_trades": 123,
    "trips_per_year": 10.4478,
    "mean_days_between": 6.0,
    "mean_hold_days": 18.1,
    "median_hold_days": 4.0,
    "hit_rate_pct": 64.2276,
    "avg_win_pct": 2.1493,
    "avg_loss_pct": -2.0094,
    "profit_factor": 1.9204,
    "expected_ret_per_trip_pct": 0.6616,
    "median_ret_per_trip_pct": 0.0094
  },
  "buy_and_hold": {
    "cagr_pct": 13.6947,
    "ann_vol_pct": 17.5173,
    "max_drawdown_pct": -33.7173,
    "calmar": 0.4062,
    "sharpe": 0.8221,
    "sortino": 1.0062,
    "skewness": -0.3043,
    "excess_kurtosis": 14.1045
  }
}