{
  "last_updated": "2026-03-19",
  "oos_start": "2014-07-29",
  "oos_end": "2026-03-19",
  "strategy": {
    "cagr_pct": 9.216,
    "ann_vol_pct": 10.9093,
    "max_drawdown_pct": -16.7963,
    "calmar": 0.5487,
    "sharpe": 0.8646,
    "sortino": 0.9362,
    "skewness": -0.7282,
    "excess_kurtosis": 9.5772,
    "exposure_long_pct": 75.2732,
    "exposure_tbill_pct": 24.7268,
    "n_trades": 121,
    "trips_per_year": 10.3964,
    "mean_days_between": 6.0,
    "mean_hold_days": 18.2,
    "median_hold_days": 4.0,
    "hit_rate_pct": 63.6364,
    "avg_win_pct": 2.1155,
    "avg_loss_pct": -2.0365,
    "profit_factor": 1.8602,
    "expected_ret_per_trip_pct": 0.6225,
    "median_ret_per_trip_pct": 0.0077
  },
  "buy_and_hold": {
    "cagr_pct": 12.8308,
    "ann_vol_pct": 17.5312,
    "max_drawdown_pct": -33.7172,
    "calmar": 0.3805,
    "sharpe": 0.7781,
    "sortino": 0.9504,
    "skewness": -0.3073,
    "excess_kurtosis": 14.2122
  }
}